README.md
setup.py
tatum/__init__.py
tatum/utils.py
tatum.egg-info/PKG-INFO
tatum.egg-info/SOURCES.txt
tatum.egg-info/dependency_links.txt
tatum.egg-info/not-zip-safe
tatum.egg-info/top_level.txt