Metadata-Version: 1.1
Name: tatum
Version: 0.1
Summary: A Simple Chaining Wrapper for PyMongo Aggregated Queries
Home-page: http://github.com/sheeloroee/tatum
Author: SheeloRoee
Author-email: roee.sheelo@gmail.com
License: MIT
Keywords: nosql mongo pymongo mongodb queries chaining aggregation wrapper db
Platform: UNKNOWN
Classifier: License :: OSI Approved :: MIT License
Classifier: Programming Language :: Python :: 2.7
Classifier: Operating System :: OS Independent
